pppf_accessories/__init__.py
pppf_accessories/blast.py
pppf_accessories/formatting.py
pppf_clusters/__init__.py
pppf_clusters/cluster.py
pppf_clusters/cluster_functions.py
pppf_clusters/load_clusters_to_database.py
pppf_databases/__init__.py
pppf_databases/database_handles.py
pppf_databases/db_to_fasta.py
pppf_databases/define_database_tables.py
pppf_databases/download_databases.py
pppf_databases/load_sequences_from_genbank.py
pppf_db/__init__.py
pppf_db/database_handles.py
pppf_db/db_paths.py
pppf_db/dump_protein_fasta.py
pppf_db/genomes.py
pppf_db/protein.py
pppf_db/proteins.py
pppf_lib/__init__.py
pppf_lib/bit_score.py
pppf_lib/cluster_summary.py
pppf_lib/functions.py
pppf_lib/genbank.py
pppf_lib/genbank_download.py
pppf_lib/genbank_search.py
pppf_lib/import_genbank_data.py
pppfdb/__init__.py
pppfdb/database_handles.py
pppfdb/db_paths.py
pppfdb/protein.py
PPPF-0.1.0.dist-info/LICENSE
PPPF-0.1.0.dist-info/METADATA
PPPF-0.1.0.dist-info/WHEEL
PPPF-0.1.0.dist-info/entry_points.txt
PPPF-0.1.0.dist-info/top_level.txt
PPPF-0.1.0.dist-info/RECORD
