Metadata-Version: 2.1
Name: PPPF
Version: 0.1.0
Summary: Probabilistic Phage Protein Functions: Phage genomes and their annotations 
Home-page: https://linsalrob.github.io/PPPF/
Author: Rob Edwards
Author-email: raedwards@gmail.com
License: MIT License
Platform: UNKNOWN
Classifier: Programming Language :: Python :: 3
Classifier: License :: OSI Approved :: MIT License
Classifier: Operating System :: OS Independent
Classifier: Development Status :: 2 - Pre-Alpha
Classifier: Intended Audience :: Science/Research
Classifier: Topic :: Scientific/Engineering :: Bio-Informatics
Requires-Python: >=3.6
Requires-Dist: jsonpickle
Requires-Dist: biopython
Requires-Dist: requests
